theovib/__init__.py
theovib/aimall_tools.py
theovib/input.py
theovib/internal.py
theovib/ir.py
theovib/matrices.py
theovib/molecule.py
theovib/ptable.py
theovib-0.0.5.dist-info/LICENSE
theovib-0.0.5.dist-info/METADATA
theovib-0.0.5.dist-info/WHEEL
theovib-0.0.5.dist-info/top_level.txt
theovib-0.0.5.dist-info/RECORD
