Metadata-Version: 2.1
Name: theovib
Version: 0.0.5
Summary: Tools for molecular vibrations analysis
Home-page: https://github.com/ljduarte/theovib
Author: L. J. Duarte
Author-email: leo.j.duarte49@gmail.com
Project-URL: Bug Tracker, https://github.com/ljduarte/theovib/issues
Classifier: Programming Language :: Python :: 3
Classifier: License :: OSI Approved :: MIT License
Classifier: Operating System :: OS Independent
Requires-Python: >=3.6
License-File: LICENSE
